{
  "name": "vuemix",
  "version": "0.1.0",
  "lockfileVersion": 2,
  "requires": true,
  "packages": {
    "": {
      "name": "vuemix",
      "version": "0.1.0",
      "license": "MIT",
      "dependencies": {
        "@vue/server-renderer": "3.2.26",
        "cookie-parser": "1.4.6",
 "express": "4.17.2",
        "node-fetch": "3.1.1",
        "vue": "3.2.26",
        "cookie-parser": "1.4.6",
        "express": "4.17.2",
      },
      "devDependencies": {
        "@vue/compiler-sfc": "3.2.31",
        "concurrently": "7.0.0",
        "cypress": "9.3.1",
        "esbuild": "0.14.11",
        "esbuild-plugin-vue-next": "0.1.4",
        "eslint": "8.7.0",
        "eslint-config-airbnb": "19.0.4",
        "eslint-config-prettier": "8.3.0",
        "eslint-plugin-cypress": "2.12.1",
        "eslint-plugin-vue": "8.3.0",
        "husky": "7.0.4",
        "nodemon": "2.0.15",
        "prettier": "2.5.1",
        "start-server-and-test": "1.14.0"
      }
    },
    "node_modules/@babel/parser": {
      "version": "7.16.10",
      "resolved": "https://registry.npmjs.org/@babel/parser/-/parser-7.16.10.tgz",
      "integrity": "sha512-Sm/S9Or6nN8uiFsQU1yodyDW3MWXQhFeqzMPM+t8MJjM+pLsnFVxFZzkpXKvUXh+Gz9cbMoYYs484+Jw/NTEFQ==",
      "bin": {
        "parser": "bin/babel-parser.js"
      },
      "engines": {
        "node": ">=6.0.0"
      }
    },
    "node_modules/@babel/runtime": {
      "version": "7.16.7",
      "resolved": "https://registry.npmjs.org/@babel/runtime/-/runtime-7.16.7.tgz",
      "integrity": "sha512-9E9FJowqAsytyOY6LG+1KuueckRL+aQW+mKvXRXnuFGyRAyepJPmEo9vgMfXUA6O9u3IeEdv9MAkppFcaQwogQ==",
      "dev": true,
      "peer": true,
